{
  "name": "surrealql-theme",
  "semanticHighlighting": true,
  "tokenColors": [
    {
      "name": "Global settings",
      "settings": {
        "background": "#151517",
        "foreground": "#ffffff"
      }
    },
    {
      "name": "String",
      "scope": "string",
      "settings": {
        "foreground": "#C3E88D"
      }
    },
    {
      "name": "Punctuation",
      "scope": "punctuation, constant.other.symbol",
      "settings": {
        "foreground": "#89DDFF"
      }
    },
    {
      "name": "String Escape",
      "scope": "constant.character.escape, text.html constant.character.entity.named",
      "settings": {
        "foreground": "#A6ACCD"
      }
    },
    {
      "name": "Boolean",
      "scope": "constant.language.boolean",
      "settings": {
        "foreground": "#ff9cac"
      }
    },
    {
      "name": "Number",
      "scope": "constant.numeric",
      "settings": {
        "foreground": "#F78C6C"
      }
    },
    {
      "name": "Variable",
      "scope": "variable, variable.parameter, support.variable, variable.language, support.constant, meta.definition.variable entity.name.function, meta.function-call.arguments",
      "settings": {
        "foreground": "#A6ACCD"
      }
    },
    {
      "name": "Other Keyword",
      "scope": "keyword.other",
      "settings": {
        "foreground": "#F78C6C"
      }
    },
    {
      "name": "Keyword",
      "scope": "keyword, modifier, variable.language.this, support.type.object, constant.language",
      "settings": {
        "foreground": "#89DDFF"
      }
    },
    {
      "name": "Function call",
      "scope": "entity.name.function, support.function",
      "settings": {
        "foreground": "#82AAFF"
      }
    },
    {
      "name": "Storage",
      "scope": "storage.type, storage.modifier, storage.control",
      "settings": {
        "foreground": "#C792EA"
      }
    },
    {
      "name": "Modules",
      "scope": "support.module, support.node",
      "settings": {
        "foreground": "#f07178",
        "fontStyle": "italic"
      }
    },
    {
      "name": "Type",
      "scope": "support.type, constant.other.key",
      "settings": {
        "foreground": "#FFCB6B"
      }
    },
    {
      "name": "Type",
      "scope": "entity.name.type, entity.other.inherited-class, entity.other",
      "settings": {
        "foreground": "#FFCB6B"
      }
    },
    {
      "name": "Comment",
      "scope": "comment",
      "settings": {
        "foreground": "#464B5D",
        "fontStyle": "italic"
      }
    },
    {
      "name": "Comment",
      "scope": "comment punctuation.definition.comment, string.quoted.docstring",
      "settings": {
        "foreground": "#464B5D",
        "fontStyle": "italic"
      }
    },
    {
      "name": "Punctuation",
      "scope": "punctuation",
      "settings": {
        "foreground": "#89DDFF"
      }
    },
    {
      "name": "Class",
      "scope": "entity.name, entity.name.type.class, support.type, support.class, meta.use",
      "settings": {
        "foreground": "#FFCB6B"
      }
    },
    {
      "name": "Class variable",
      "scope": "variable.object.property, meta.field.declaration entity.name.function",
      "settings": {
        "foreground": "#f07178"
      }
    },
    {
      "name": "Class method",
      "scope": "meta.definition.method entity.name.function",
      "settings": {
        "foreground": "#f07178"
      }
    },
    {
      "name": "Function definition",
      "scope": "meta.function entity.name.function",
      "settings": {
        "foreground": "#82AAFF"
      }
    },
    {
      "name": "Template expression",
      "scope": "template.expression.begin, template.expression.end, punctuation.definition.template-expression.begin, punctuation.definition.template-expression.end",
      "settings": {
        "foreground": "#89DDFF"
      }
    },
    {
      "name": "Reset embedded/template expression colors",
      "scope": "meta.embedded, source.groovy.embedded, meta.template.expression",
      "settings": {
        "foreground": "#A6ACCD"
      }
    },
    {
      "name": "YAML key",
      "scope": "entity.name.tag.yaml",
      "settings": {
        "foreground": "#f07178"
      }
    },
    {
      "name": "JSON key",
      "scope": "meta.object-literal.key, meta.object-literal.key string, support.type.property-name.json",
      "settings": {
        "foreground": "#f07178"
      }
    },
    {
      "name": "JSON constant",
      "scope": "constant.language.json",
      "settings": {
        "foreground": "#89DDFF"
      }
    },
    {
      "name": "CSS class",
      "scope": "entity.other.attribute-name.class",
      "settings": {
        "foreground": "#FFCB6B"
      }
    },
    {
      "name": "CSS ID",
      "scope": "entity.other.attribute-name.id",
      "settings": {
        "foreground": "#F78C6C"
      }
    },
    {
      "name": "CSS tag",
      "scope": "source.css entity.name.tag",
      "settings": {
        "foreground": "#FFCB6B"
      }
    },
    {
      "name": "CSS properties",
      "scope": "support.type.property-name.css",
      "settings": {
        "foreground": "#B2CCD6"
      }
    },
    {
      "name": "HTML tag outer",
      "scope": "meta.tag, punctuation.definition.tag",
      "settings": {
        "foreground": "#89DDFF"
      }
    },
    {
      "name": "HTML tag inner",
      "scope": "entity.name.tag",
      "settings": {
        "foreground": "#f07178"
      }
    },
    {
      "name": "HTML tag attribute",
      "scope": "entity.other.attribute-name",
      "settings": {
        "foreground": "#C792EA"
      }
    },
    {
      "name": "HTML entities",
      "scope": "punctuation.definition.entity.html",
      "settings": {
        "foreground": "#A6ACCD"
      }
    },
    {
      "name": "Markdown heading",
      "scope": "markup.heading",
      "settings": {
        "foreground": "#89DDFF"
      }
    },
    {
      "name": "Markdown link text",
      "scope": "text.html.markdown meta.link.inline, meta.link.reference",
      "settings": {
        "foreground": "#f07178"
      }
    },
    {
      "name": "Markdown list item",
      "scope": "text.html.markdown beginning.punctuation.definition.list",
      "settings": {
        "foreground": "#89DDFF"
      }
    },
    {
      "name": "Markdown italic",
      "scope": "markup.italic",
      "settings": {
        "foreground": "#f07178",
        "fontStyle": "italic"
      }
    },
    {
      "name": "Markdown bold",
      "scope": "markup.bold",
      "settings": {
        "foreground": "#f07178",
        "fontStyle": "bold"
      }
    },
    {
      "name": "Markdown bold italic",
      "scope": "markup.bold markup.italic, markup.italic markup.bold",
      "settings": {
        "foreground": "#f07178",
        "fontStyle": "italic bold"
      }
    },
    {
      "name": "Markdown code block",
      "scope": "markup.fenced_code.block.markdown punctuation.definition.markdown",
      "settings": {
        "foreground": "#C3E88D"
      }
    },
    {
      "name": "Markdown inline code",
      "scope": "markup.inline.raw.string.markdown",
      "settings": {
        "foreground": "#C3E88D"
      }
    },
    {
      "name": "INI property name",
      "scope": "keyword.other.definition.ini",
      "settings": {
        "foreground": "#f07178"
      }
    },
    {
      "name": "INI section title",
      "scope": "entity.name.section.group-title.ini",
      "settings": {
        "foreground": "#89DDFF"
      }
    },
    {
      "name": "C# class",
      "scope": "source.cs meta.class.identifier storage.type",
      "settings": {
        "foreground": "#FFCB6B"
      }
    },
    {
      "name": "C# class method",
      "scope": "source.cs meta.method.identifier entity.name.function",
      "settings": {
        "foreground": "#f07178"
      }
    },
    {
      "name": "C# function call",
      "scope": "source.cs meta.method-call meta.method, source.cs entity.name.function",
      "settings": {
        "foreground": "#82AAFF"
      }
    },
    {
      "name": "C# type",
      "scope": "source.cs storage.type",
      "settings": {
        "foreground": "#FFCB6B"
      }
    },
    {
      "name": "C# return type",
      "scope": "source.cs meta.method.return-type",
      "settings": {
        "foreground": "#FFCB6B"
      }
    },
    {
      "name": "C# preprocessor",
      "scope": "source.cs meta.preprocessor",
      "settings": {
        "foreground": "#464B5D"
      }
    },
    {
      "name": "C# namespace",
      "scope": "source.cs entity.name.type.namespace",
      "settings": {
        "foreground": "#A6ACCD"
      }
    },
    {
      "name": "JSX Text",
      "scope": "meta.jsx.children, SXNested",
      "settings": {
        "foreground": "#A6ACCD"
      }
    },
    {
      "name": "JSX Components name",
      "scope": "support.class.component",
      "settings": {
        "foreground": "#FFCB6B"
      }
    },
    {
      "name": "C-related Block Level Variables",
      "scope": "source.cpp meta.block variable.other",
      "settings": {
        "foreground": "#A6ACCD"
      }
    },
    {
      "name": "Member Access Meta",
      "scope": "source.python meta.member.access.python",
      "settings": {
        "foreground": "#f07178"
      }
    },
    {
      "name": "Function Call",
      "scope": "source.python meta.function-call.python, meta.function-call.arguments",
      "settings": {
        "foreground": "#82AAFF"
      }
    },
    {
      "name": "Blocks",
      "scope": "meta.block",
      "settings": {
        "foreground": "#f07178"
      }
    },
    {
      "name": "Function Call",
      "scope": "entity.name.function.call",
      "settings": {
        "foreground": "#82AAFF"
      }
    },
    {
      "name": "Namespaces",
      "scope": "source.php support.other.namespace, source.php meta.use support.class",
      "settings": {
        "foreground": "#A6ACCD"
      }
    },
    {
      "name": "Constant keywords",
      "scope": "constant.keyword",
      "settings": {
        "foreground": "#89DDFF",
        "fontStyle": "italic"
      }
    },
    {
      "name": "Entity name",
      "scope": "entity.name.function",
      "settings": {
        "foreground": "#82AAFF"
      }
    },
    {
      "name": "Global settings",
      "settings": {
        "background": "#151517",
        "foreground": "#ffffff"
      }
    },
    {
      "name": "Markup Deleted",
      "scope": ["markup.deleted"],
      "settings": {
        "foreground": "#f07178"
      }
    },
    {
      "name": "Markup Inserted",
      "scope": ["markup.inserted"],
      "settings": {
        "foreground": "#C3E88D"
      }
    },
    {
      "name": "Markup Underline",
      "scope": ["markup.underline"],
      "settings": {
        "fontStyle": "underline"
      }
    },
    {
      "name": "Keyword Control",
      "scope": ["keyword.control"],
      "settings": {
        "foreground": "#89DDFF",
        "fontStyle": "italic"
      }
    },
    {
      "name": "Markdown - Blockquote",
      "scope": ["markup.quote"],
      "settings": {
        "fontStyle": "italic",
        "foreground": "#89DDFF"
      }
    },
    {
      "name": "Markdown - Fenced Language",
      "scope": ["markup.fenced_code.block"],
      "settings": {
        "foreground": "#A6ACCD90"
      }
    },
    {
      "name": "Markdown - Blockquote Punctuation",
      "scope": ["punctuation.definition.quote"],
      "settings": {
        "foreground": "#ff9cac"
      }
    },
    {
      "name": "JSON Key - Level 0",
      "scope": [
        "meta.structure.dictionary.json support.type.property-name.json"
      ],
      "settings": {
        "foreground": "#C792EA"
      }
    },
    {
      "name": "JSON Key - Level 1",
      "scope": [
        "meta.structure.dictionary.json meta.structure.dictionary.value.json meta.structure.dictionary.json support.type.property-name.json"
      ],
      "settings": {
        "foreground": "#FFCB6B"
      }
    },
    {
      "name": "JSON Key - Level 2",
      "scope": [
        "meta.structure.dictionary.json meta.structure.dictionary.value.json meta.structure.dictionary.json meta.structure.dictionary.value.json meta.structure.dictionary.json support.type.property-name.json"
      ],
      "settings": {
        "foreground": "#F78C6C"
      }
    },
    {
      "name": "JSON Key - Level 3",
      "scope": [
        "meta.structure.dictionary.json meta.structure.dictionary.value.json meta.structure.dictionary.json meta.structure.dictionary.value.json meta.structure.dictionary.json meta.structure.dictionary.value.json meta.structure.dictionary.json support.type.property-name.json"
      ],
      "settings": {
        "foreground": "#f07178"
      }
    },
    {
      "name": "JSON Key - Level 4",
      "scope": [
        "meta.structure.dictionary.json meta.structure.dictionary.value.json meta.structure.dictionary.json meta.structure.dictionary.value.json meta.structure.dictionary.json meta.structure.dictionary.value.json meta.structure.dictionary.json meta.structure.dictionary.value.json meta.structure.dictionary.json support.type.property-name.json"
      ],
      "settings": {
        "foreground": "#916b53"
      }
    },
    {
      "name": "JSON Key - Level 5",
      "scope": [
        "meta.structure.dictionary.json meta.structure.dictionary.value.json meta.structure.dictionary.json meta.structure.dictionary.value.json meta.structure.dictionary.json meta.structure.dictionary.value.json meta.structure.dictionary.json meta.structure.dictionary.value.json meta.structure.dictionary.json meta.structure.dictionary.value.json meta.structure.dictionary.json support.type.property-name.json"
      ],
      "settings": {
        "foreground": "#82AAFF"
      }
    },
    {
      "name": "JSON Key - Level 6",
      "scope": [
        "meta.structure.dictionary.json meta.structure.dictionary.value.json meta.structure.dictionary.json meta.structure.dictionary.value.json meta.structure.dictionary.json meta.structure.dictionary.value.json meta.structure.dictionary.json meta.structure.dictionary.value.json meta.structure.dictionary.json meta.structure.dictionary.value.json meta.structure.dictionary.json meta.structure.dictionary.value.json meta.structure.dictionary.json support.type.property-name.json"
      ],
      "settings": {
        "foreground": "#ff9cac"
      }
    },
    {
      "name": "JSON Key - Level 7",
      "scope": [
        "meta.structure.dictionary.json meta.structure.dictionary.value.json meta.structure.dictionary.json meta.structure.dictionary.value.json meta.structure.dictionary.json meta.structure.dictionary.value.json meta.structure.dictionary.json meta.structure.dictionary.value.json meta.structure.dictionary.json meta.structure.dictionary.value.json meta.structure.dictionary.json meta.structure.dictionary.value.json meta.structure.dictionary.json meta.structure.dictionary.value.json meta.structure.dictionary.json support.type.property-name.json"
      ],
      "settings": {
        "foreground": "#C792EA"
      }
    },
    {
      "name": "JSON Key - Level 8",
      "scope": [
        "meta.structure.dictionary.json meta.structure.dictionary.value.json meta.structure.dictionary.json meta.structure.dictionary.value.json meta.structure.dictionary.json meta.structure.dictionary.value.json meta.structure.dictionary.json meta.structure.dictionary.value.json meta.structure.dictionary.json meta.structure.dictionary.value.json meta.structure.dictionary.json meta.structure.dictionary.value.json meta.structure.dictionary.json meta.structure.dictionary.value.json meta.structure.dictionary.json meta.structure.dictionary.value.json meta.structure.dictionary.json support.type.property-name.json"
      ],
      "settings": {
        "foreground": "#C3E88D"
      }
    },

    {
      "name": "SurrealQL comment",
      "scope": "source.surrealql comment",
      "settings": {
        "foreground": "#737e98"
      }
    },
    {
      "name": "SurrealQL punctuation",
      "scope": "source.surrealql punctuation",
      "settings": {
        "foreground": "#ffffff"
      }
    },
    {
      "name": "SurrealQL variable",
      "scope": "source.surrealql variable",
      "settings": {
        "foreground": "#ffde00"
      }
    },
    {
      "name": "SurrealQL operator",
      "scope": "source.surrealql operator.operator",
      "settings": {
        "foreground": "#ff009e"
      }
    },
    {
      "name": "SurrealQL keyword",
      "scope": "source.surrealql keyword.control",
      "settings": {
        "foreground": "#ff009e"
      }
    },
    {
      "name": "SurrealQL cast",
      "scope": "source.surrealql entity.name.type",
      "settings": {
        "foreground": "#999999"
      }
    },
    {
      "name": "SurrealQL string",
      "scope": "source.surrealql string",
      "settings": {
        "foreground": "#00ff6e"
      }
    },
    {
      "name": "SurrealQL number",
      "scope": "source.surrealql constant.numeric",
      "settings": {
        "foreground": "#00dbff"
      }
    },
    {
      "name": "SurrealQL duration",
      "scope": "source.surrealql constant.other",
      "settings": {
        "foreground": "#00dbff"
      }
    },
    {
      "name": "SurrealQL boolean",
      "scope": "source.surrealql constant.language.boolean",
      "settings": {
        "foreground": "#9d2fff"
      }
    },
    {
      "name": "SurrealQL nothing",
      "scope": "source.surrealql constant.language.void",
      "settings": {
        "foreground": "#9d2fff"
      }
    },
    {
      "name": "SurrealQL function",
      "scope": "source.surrealql support.function",
      "settings": {
        "foreground": "#ff9b67"
      }
    },
    {
      "name": "SurrealQL record",
      "scope": "source.surrealql entity.name.class",
      "settings": {
        "foreground": "#0084ff"
      }
    },
    {
      "name": "SurrealQL object key",
      "scope": "source.surrealql meta.object-literal.key",
      "settings": {
        "foreground": "#0084ff"
      }
    }
  ]
}
